DeeperAI/__init__.py
DeeperAI/core.py
DeeperAI-1.0.2.dist-info/LICENSE
DeeperAI-1.0.2.dist-info/METADATA
DeeperAI-1.0.2.dist-info/WHEEL
DeeperAI-1.0.2.dist-info/top_level.txt
DeeperAI-1.0.2.dist-info/RECORD
