Metadata-Version: 2.1
Name: DeeperAI
Version: 1.0.2
Summary: A comprehensive AI library featuring deep learning, reinforcement learning, computer vision, and more.
Home-page: https://github.com/mr-r0ot/DeeperAI
Author: Muhammad Taha Gorji
Author-email: MohammadTahaGorjiProfile@gmail.com
Classifier: Programming Language :: Python :: 3
Classifier: Operating System :: OS Independent
Requires-Python: >=3.6
License-File: LICENSE
Requires-Dist: rich >=10.0.0
Requires-Dist: requests >=2.25.1
Requires-Dist: beautifulsoup4 >=4.9.3
Requires-Dist: googlesearch-python >=1.1.0
Requires-Dist: Pillow >=8.0.0
Requires-Dist: torch >=1.8.0
Requires-Dist: nltk >=3.6.0
Requires-Dist: joblib >=1.0.1
Requires-Dist: spacy >=3.0.0
Requires-Dist: numpy >=1.19.2
Requires-Dist: matplotlib >=3.3.3
Requires-Dist: opencv-python >=4.5.1.48
Requires-Dist: transformers >=4.0.0
Requires-Dist: langdetect >=1.0.8
Requires-Dist: textblob >=0.15.3
Requires-Dist: scikit-learn >=0.24.1
Requires-Dist: tensorflow >=2.4.1
Requires-Dist: selenium >=3.141.0
Requires-Dist: scipy >=1.5.2
